contractions/__init__.py
contractions/_version.py
contractions/api.py
contractions/bootstrap.py
contractions/extension.py
contractions/file_loader.py
contractions/matcher.py
contractions/processor.py
contractions/state.py
contractions/transformer.py
contractions/validation.py
contractions/data/__init__.py
contractions/data/contractions_dict.json
contractions/data/leftovers_dict.json
contractions/data/safety_keys.json
contractions/data/slang_dict.json
sane_contractions-0.3.2.dist-info/licenses/LICENSE
sane_contractions-0.3.2.dist-info/METADATA
sane_contractions-0.3.2.dist-info/WHEEL
sane_contractions-0.3.2.dist-info/top_level.txt
sane_contractions-0.3.2.dist-info/RECORD
