Metadata-Version: 2.4
Name: sane-contractions
Version: 0.3.2
Summary: Enhanced fork of contractions library - Expands English contractions with improved performance and new features
Author-email: Jeremy Bruns <99199491+devjerry0@users.noreply.github.com>
Maintainer-email: Jeremy Bruns <99199491+devjerry0@users.noreply.github.com>
License-Expression: MIT
Project-URL: Homepage, https://github.com/devjerry0/sane-contractions
Project-URL: Documentation, https://github.com/devjerry0/sane-contractions#readme
Project-URL: Repository, https://github.com/devjerry0/sane-contractions.git
Project-URL: Bug Tracker, https://github.com/devjerry0/sane-contractions/issues
Project-URL: Original Project, https://github.com/kootenpv/contractions
Keywords: contractions,nlp,text-processing,slang,text-expansion
Classifier: Development Status :: 4 - Beta
Classifier: Intended Audience :: Developers
Classifier: Intended Audience :: Customer Service
Classifier: Intended Audience :: System Administrators
Classifier: Operating System :: Microsoft
Classifier: Operating System :: MacOS :: MacOS X
Classifier: Operating System :: Unix
Classifier: Operating System :: POSIX
Classifier: Programming Language :: Python
Classifier: Programming Language :: Python :: 3
Classifier: Programming Language :: Python :: 3.10
Classifier: Programming Language :: Python :: 3.11
Classifier: Programming Language :: Python :: 3.12
Classifier: Programming Language :: Python :: 3.13
Classifier: Programming Language :: Python :: 3.14
Classifier: Topic :: Software Development
Classifier: Topic :: Software Development :: Libraries
Classifier: Topic :: Software Development :: Libraries :: Python Modules
Classifier: Topic :: System :: Software Distribution
Classifier: Topic :: System :: Systems Administration
Classifier: Topic :: Text Processing :: Linguistic
Classifier: Topic :: Utilities
Requires-Python: >=3.10
License-File: LICENSE
Requires-Dist: textsearch>=0.0.24
Provides-Extra: dev
Requires-Dist: pytest>=7.0; extra == "dev"
Requires-Dist: pytest-cov>=4.0; extra == "dev"
Requires-Dist: ruff>=0.1.0; extra == "dev"
Requires-Dist: mypy>=1.0; extra == "dev"
Requires-Dist: build>=1.0; extra == "dev"
Requires-Dist: twine>=4.0; extra == "dev"
Dynamic: license-file
